openwebui_token_tracking/__init__.py
openwebui_token_tracking/credit_groups.py
openwebui_token_tracking/model_pricing.py
openwebui_token_tracking/models.py
openwebui_token_tracking/settings.py
openwebui_token_tracking/sponsored.py
openwebui_token_tracking/tracking.py
openwebui_token_tracking/user.py
openwebui_token_tracking/actions/__init__.py
openwebui_token_tracking/actions/credit_balance.py
openwebui_token_tracking/cli/__init__.py
openwebui_token_tracking/cli/main.py
openwebui_token_tracking/cli/commands/credit_group.py
openwebui_token_tracking/cli/commands/database.py
openwebui_token_tracking/cli/commands/pricing.py
openwebui_token_tracking/cli/commands/settings.py
openwebui_token_tracking/cli/commands/sponsored.py
openwebui_token_tracking/cli/commands/user.py
openwebui_token_tracking/db/__init__.py
openwebui_token_tracking/db/base.py
openwebui_token_tracking/db/credit_group.py
openwebui_token_tracking/db/db.py
openwebui_token_tracking/db/model_pricing.py
openwebui_token_tracking/db/settings.py
openwebui_token_tracking/db/sponsored.py
openwebui_token_tracking/db/token_usage.py
openwebui_token_tracking/db/user.py
openwebui_token_tracking/migrations/alembic/env.py
openwebui_token_tracking/migrations/alembic/script.py.mako
openwebui_token_tracking/migrations/alembic/versions/036cd1c4af2d_create_base_settings_table.py
openwebui_token_tracking/migrations/alembic/versions/10d29ec2fd0a_create_sponsored_allowance_table.py
openwebui_token_tracking/migrations/alembic/versions/6099739cae0b_create_model_pricing_table.py
openwebui_token_tracking/migrations/alembic/versions/99fb3ad5e0e7_create_table_token_usage_log.py
openwebui_token_tracking/migrations/alembic/versions/a118dd7f6b7f_add_sponsored_allowance_column.py
openwebui_token_tracking/migrations/alembic/versions/c46ceb8649c3_create_credit_group_table.py
openwebui_token_tracking/pipes/__init__.py
openwebui_token_tracking/pipes/anthropic.py
openwebui_token_tracking/pipes/base_tracked_pipe.py
openwebui_token_tracking-0.1.10.dist-info/METADATA
openwebui_token_tracking-0.1.10.dist-info/WHEEL
openwebui_token_tracking-0.1.10.dist-info/entry_points.txt
openwebui_token_tracking-0.1.10.dist-info/licenses/LICENSE
openwebui_token_tracking-0.1.10.dist-info/RECORD
