Metadata-Version: 2.4
Name: openwebui-token-tracking
Version: 0.1.10
Summary: A library to facilitate token tracking and limiting in Open WebUI.
Author-email: Simon Stone <simon.stone@dartmouth.edu>
License-File: LICENSE
Requires-Python: >=3.11
Requires-Dist: alembic>=1.14.0
Requires-Dist: click>=8.1.8
Requires-Dist: google-generativeai>=0.7.2
Requires-Dist: open-webui>=0.6.0
Requires-Dist: pydantic>=2.9.2
Requires-Dist: pytest>=8.3.4
Requires-Dist: python-dotenv>=1.0.1
Requires-Dist: sqlalchemy[asyncio]>=2.0.32
Provides-Extra: docs
Requires-Dist: myst-parser>=4.0.1; extra == 'docs'
Requires-Dist: sphinx-autodoc-typehints>=3.0.1; extra == 'docs'
Requires-Dist: sphinx-rtd-theme>=3.0.2; extra == 'docs'
Requires-Dist: sphinx>=8.1.3; extra == 'docs'
